README.md
setup.py
loto_online.py.egg-info/PKG-INFO
loto_online.py.egg-info/SOURCES.txt
loto_online.py.egg-info/dependency_links.txt
loto_online.py.egg-info/requires.txt
loto_online.py.egg-info/top_level.txt
lotoonline/__init__.py
lotoonline/authorization.py
lotoonline/friend.py
lotoonline/game.py
lotoonline/lotoonline.py
lotoonline/socket_listener.py
lotoonline/utils/__init__.py
lotoonline/utils/objects.py