Metadata-Version: 2.1
Name: loto-online.py
Version: 1.0.0
Summary: A library to create Loto Online bots.
Home-page: https://github.com/Zakovskiy/loto_online.py
Author: Zakovskiy
Author-email: gogrugu@gmail.com
License: MIT
Download-URL: https://github.com/Zakovskiy/loto_online.py/tarball/master
Keywords: loto,online,loto_online.py,loto.py,loto-bot,rstgame,rstgames,api,socket,python,python3,python3.x,zakovskiy,official
Platform: UNKNOWN
